pyClimateSciTool/__init__.py
pyClimateSciTool/pyClimateSciTool.py
pyClimateSciTool-1.1.0.dist-info/LICENSE.txt
pyClimateSciTool-1.1.0.dist-info/METADATA
pyClimateSciTool-1.1.0.dist-info/WHEEL
pyClimateSciTool-1.1.0.dist-info/top_level.txt
pyClimateSciTool-1.1.0.dist-info/RECORD
