Metadata-Version: 2.1
Name: pyClimateSciTool
Version: 1.1.0
Summary: A toolkit including useful functions for climate science
Home-page: UNKNOWN
Author: HE Yanfeng
Author-email: 412694462@qq.com
License: MIT
Keywords: python,climate science,climate data processing
Platform: UNKNOWN
Classifier: Development Status :: 1 - Planning
Classifier: Intended Audience :: Developers
Classifier: Programming Language :: Python :: 3
Classifier: Operating System :: Unix
Classifier: Operating System :: MacOS :: MacOS X
Classifier: Operating System :: Microsoft :: Windows
License-File: LICENSE.txt
